chat_box_streamlit/__init__.py
chat_box_streamlit/frontend/dist/bootstrap.min.css
chat_box_streamlit/frontend/dist/bot.png
chat_box_streamlit/frontend/dist/index.html
chat_box_streamlit/frontend/dist/send.svg
chat_box_streamlit/frontend/dist/user.png
chat_box_streamlit/frontend/dist/assets/index-ba3e6331.js
chat_box_streamlit-0.0.95.dist-info/LICENSE
chat_box_streamlit-0.0.95.dist-info/METADATA
chat_box_streamlit-0.0.95.dist-info/WHEEL
chat_box_streamlit-0.0.95.dist-info/top_level.txt
chat_box_streamlit-0.0.95.dist-info/RECORD
