Metadata-Version: 2.1
Name: chat-box-streamlit
Version: 0.0.95
Summary: Seamlessly visualize engaging conversations in a sleek ChatBox.
Home-page: https://github.com/SSK-14/Streamlit-Chatbox
Author: SSK-14
Author-email: sanjaykumar1481999@gmail.com
Requires-Python: >=3.6
License-File: LICENSE
Requires-Dist: streamlit (>=0.63)
